censusgeocode/__init__.py
censusgeocode/__main__.py
censusgeocode/censusgeocode.py
censusgeocode-0.5.2.dist-info/METADATA
censusgeocode-0.5.2.dist-info/WHEEL
censusgeocode-0.5.2.dist-info/entry_points.txt
censusgeocode-0.5.2.dist-info/top_level.txt
censusgeocode-0.5.2.dist-info/RECORD
