Metadata-Version: 2.1
Name: censusgeocode
Version: 0.5.2
Summary: Thin Python wrapper for the US Census Geocoder
Home-page: https://github.com/fitnr/censusgeocode
Author: Neil Freeman
Author-email: contact@fakeisthenewreal.org
License: GNU General Public License v3 (GPLv3)
Keywords: census,geocode,api
Platform: UNKNOWN
Classifier: Development Status :: 4 - Beta
Classifier: Intended Audience :: Developers
Classifier: License :: OSI Approved :: GNU General Public License v3 (GPLv3)
Classifier: Natural Language :: English
Classifier: Programming Language :: Python :: 3.7
Classifier: Programming Language :: Python :: 3.8
Classifier: Programming Language :: Python :: 3.9
Classifier: Programming Language :: Python :: 3.10
Classifier: Operating System :: OS Independent
Requires-Python: <4,>=3.6
Provides-Extra: tests
